fabric_cm/__init__.py
fabric_cm/credmgr/__init__.py
fabric_cm/credmgr/openapi.json
fabric_cm/credmgr/update_swagger_stub.sh
fabric_cm/credmgr/common/__init__.py
fabric_cm/credmgr/common/exceptions.py
fabric_cm/credmgr/common/utils.py
fabric_cm/credmgr/config/__init__.py
fabric_cm/credmgr/config/config.py
fabric_cm/credmgr/core/__init__.py
fabric_cm/credmgr/core/oauth_credmgr.py
fabric_cm/credmgr/external_apis/__init__.py
fabric_cm/credmgr/external_apis/core_api.py
fabric_cm/credmgr/external_apis/ldap.py
fabric_cm/credmgr/logging/__init__.py
fabric_cm/credmgr/logging/log_helper.py
fabric_cm/credmgr/swagger_server/__init__.py
fabric_cm/credmgr/swagger_server/__main__.py
fabric_cm/credmgr/swagger_server/encoder.py
fabric_cm/credmgr/swagger_server/type_util.py
fabric_cm/credmgr/swagger_server/util.py
fabric_cm/credmgr/swagger_server/controllers/__init__.py
fabric_cm/credmgr/swagger_server/controllers/authorization_controller.py
fabric_cm/credmgr/swagger_server/controllers/default_controller.py
fabric_cm/credmgr/swagger_server/controllers/tokens_controller.py
fabric_cm/credmgr/swagger_server/controllers/version_controller.py
fabric_cm/credmgr/swagger_server/models/__init__.py
fabric_cm/credmgr/swagger_server/models/base_model_.py
fabric_cm/credmgr/swagger_server/models/decoded_token.py
fabric_cm/credmgr/swagger_server/models/jwks.py
fabric_cm/credmgr/swagger_server/models/jwks_keys.py
fabric_cm/credmgr/swagger_server/models/request.py
fabric_cm/credmgr/swagger_server/models/revoke_list.py
fabric_cm/credmgr/swagger_server/models/status200_ok_no_content.py
fabric_cm/credmgr/swagger_server/models/status200_ok_no_content_data.py
fabric_cm/credmgr/swagger_server/models/status200_ok_paginated.py
fabric_cm/credmgr/swagger_server/models/status200_ok_single.py
fabric_cm/credmgr/swagger_server/models/status400_bad_request.py
fabric_cm/credmgr/swagger_server/models/status400_bad_request_errors.py
fabric_cm/credmgr/swagger_server/models/status401_unauthorized.py
fabric_credmgr-1.9.0.dist-info/LICENSE
fabric_credmgr-1.9.0.dist-info/WHEEL
fabric_credmgr-1.9.0.dist-info/METADATA
fabric_credmgr-1.9.0.dist-info/RECORD
