Metadata-Version: 2.1
Name: fabric-credmgr
Version: 1.9.0
Summary: Fabric Credential Manager API
Keywords: Swagger,Fabric Credential Manager API
Author-email: Komal Thareja <kthare10@renci.org>
Requires-Python: >=3.9
Classifier: Programming Language :: Python :: 3
Classifier: License :: OSI Approved :: MIT License
Classifier: Operating System :: OS Independent
Requires-Dist: requests
Requires-Dist: requests_oauthlib
Requires-Dist: connexion==2.14.2
Requires-Dist: swagger-ui-bundle==0.0.9
Requires-Dist: python_dateutil
Requires-Dist: setuptools
Requires-Dist: ldap3
Requires-Dist: prometheus_client
Requires-Dist: waitress
Requires-Dist: six
Requires-Dist: cryptography
Requires-Dist: authlib
Requires-Dist: fabric_fss_utils==1.5.1
Requires-Dist: psycopg2-binary
Requires-Dist: sqlalchemy
Requires-Dist: pytest ; extra == "test"
Requires-Dist: flask_testing ; extra == "test"
Requires-Dist: coverage>=4.0.3 ; extra == "test"
Requires-Dist: nose>=1.3.7 ; extra == "test"
Requires-Dist: pluggy>=0.3.1 ; extra == "test"
Requires-Dist: py>=1.4.31 ; extra == "test"
Requires-Dist: randomize>=0.13 ; extra == "test"
Project-URL: Home, https://fabric-testbed.net/
Project-URL: Sources, https://github.com/fabric-testbed/CredentialManager
Provides-Extra: test
